ldapserver/__init__.py
ldapserver/asn1.py
ldapserver/dn.py
ldapserver/entries.py
ldapserver/exceptions.py
ldapserver/ldap.py
ldapserver/rfc4518_stringprep.py
ldapserver/server.py
ldapserver/schema/__init__.py
ldapserver/schema/definitions.py
ldapserver/schema/matching_rules.py
ldapserver/schema/syntaxes.py
ldapserver/schema/types.py
ldapserver-0.1.1.dist-info/LICENSE
ldapserver-0.1.1.dist-info/METADATA
ldapserver-0.1.1.dist-info/WHEEL
ldapserver-0.1.1.dist-info/top_level.txt
ldapserver-0.1.1.dist-info/RECORD
